MANIFEST.in
README.rst
setup.py
ci/__init__.py
ci/admin.py
ci/models.py
ci/tasks.py
ci/testrunner.py
ci/tests.py
ci/urls.py
ci/views.py
ci-server/media/bootstrap/css/bootstrap-responsive.css
ci-server/media/bootstrap/css/bootstrap-responsive.min.css
ci-server/media/bootstrap/css/bootstrap.css
ci-server/media/bootstrap/css/bootstrap.min.css
ci-server/media/bootstrap/img/glyphicons-halflings-white.png
ci-server/media/bootstrap/img/glyphicons-halflings.png
ci-server/media/bootstrap/js/bootstrap.js
ci-server/media/bootstrap/js/bootstrap.min.js
ci-server/media/images/cont.png
ci-server/media/images/cont.xcf
ci-server/media/scripts/jquery.js
ci/management/__init__.py
ci/management/commands/__init__.py
ci/management/commands/citests.py
ci/management/commands/citests_daemon.py
ci/management/commands/import_testresults.py
ci/migrations/0001_initial.py
ci/migrations/0002_auto__add_field_ciproject_manage_location__add_field_ciproject_setting.py
ci/migrations/0003_auto__add_commandgroup__add_command__add_cibranch__add_unique_cibranch.py
ci/migrations/0004_auto__del_field_testrun_project__add_field_testrun_branch__del_field_c.py
ci/migrations/0005_auto__add_field_ciproject_slug__add_field_cibranch_slug.py
ci/migrations/0006_auto__add_notificationpref.py
ci/migrations/__init__.py
ci/templates/ci/ci-branches/detail.html
ci/templates/ci/ci-projects/detail.html
ci/templates/ci/ci-projects/list.html
ci/templates/ci/notifications/list.html
ci/templatetags/__init__.py
ci/templatetags/ci_tags.py
ci/virtualenvapi/__init__.py
ci/virtualenvapi/manage.py
ci/virtualenvapi/util.py
django_ci.egg-info/PKG-INFO
django_ci.egg-info/SOURCES.txt
django_ci.egg-info/dependency_links.txt
django_ci.egg-info/requires.txt
django_ci.egg-info/top_level.txt