Metadata-Version: 1.1
Name: django-ci
Version: 0.0.5
Summary: Django continuous integration and testing
Home-page: http://pypi.python.org/pypi/django-ci/
Author: John Leith
Author-email: leith.john@gmail.com
License: UNKNOWN
Download-URL: https://bitbucket.org/freakypie/django-ci
Platform: UNKNOWN
